<annotation>
	<folder></folder>
	<filename>IMG_20220219_182841_jpg.rf.0b991aa1990e49f2f6d42a571a2f45f2.jpg</filename>
	<path>IMG_20220219_182841_jpg.rf.0b991aa1990e49f2f6d42a571a2f45f2.jpg</path>
	<source>
		<database>roboflow.com</database>
	</source>
	<size>
		<width>640</width>
		<height>640</height>
		<depth>3</depth>
	</size>
	<segmented>0</segmented>
	<object>
		<name>Sauce</name>
		<pose>Unspecified</pose>
		<truncated>0</truncated>
		<difficult>0</difficult>
		<occluded>0</occluded>
		<bndbox>
			<xmin>235</xmin>
			<xmax>424</xmax>
			<ymin>251</ymin>
			<ymax>434</ymax>
		</bndbox>
	</object>
</annotation>
